yourtools/Azkaban.py
yourtools/COS.py
yourtools/Time.py
yourtools/WeChat.py
yourtools/__init__.py
yourtools/db/__init__.py
yourtools/db/dbutils.py
yourtools/db/hive.py
yourtools/db/mysql.py
yourtools-0.6.0.data/data/requirements.txt
yourtools-0.6.0.dist-info/METADATA
yourtools-0.6.0.dist-info/WHEEL
yourtools-0.6.0.dist-info/top_level.txt
yourtools-0.6.0.dist-info/RECORD
