Metadata-Version: 2.1
Name: yourtools
Version: 0.6.0
Summary: Python helper tools
Home-page: https://pypi.org/project/yourtools/
Author: zfang
Author-email: founder517518@163.com
Classifier: Programming Language :: Python :: 3
Classifier: License :: OSI Approved :: MIT License
Classifier: Operating System :: OS Independent
Requires-Python: >=3.6
Requires-Dist: bcrypt ==4.0.1
Requires-Dist: cffi ==1.15.1
Requires-Dist: cryptography ==40.0.1
Requires-Dist: future ==0.18.3
Requires-Dist: paramiko ==3.1.0
Requires-Dist: pycparser ==2.21
Requires-Dist: PyHive ==0.6.5
Requires-Dist: PyMySQL ==1.0.2
Requires-Dist: PyNaCl ==1.5.0
Requires-Dist: python-dateutil ==2.8.2
Requires-Dist: six ==1.16.0
Requires-Dist: sshtunnel ==0.4.0
Requires-Dist: requests-toolbelt ==0.10.1
Requires-Dist: beautifulsoup4 ==4.12.0
